zap_protocol/__init__.py
zap_protocol-1.0.0.dist-info/METADATA
zap_protocol-1.0.0.dist-info/WHEEL
zap_protocol-1.0.0.dist-info/RECORD
