Metadata-Version: 2.4
Name: zap-protocol
Version: 1.0.0
Summary: ZAP - Zero-copy Application Protocol for AI agent communication. See zap-schema for the main package.
Project-URL: Homepage, https://zap-protocol.github.io/zap
Project-URL: Documentation, https://zap-protocol.github.io/zap
Project-URL: Repository, https://github.com/zap-protocol/zap
Author-email: Hanzo AI <dev@hanzo.ai>
License-Expression: MIT
Keywords: ai-agents,capnproto,mcp,protocol,rpc,zap
Classifier: Development Status :: 5 - Production/Stable
Classifier: Intended Audience :: Developers
Classifier: License :: OSI Approved :: MIT License
Classifier: Programming Language :: Python :: 3
Classifier: Programming Language :: Python :: 3.9
Classifier: Programming Language :: Python :: 3.10
Classifier: Programming Language :: Python :: 3.11
Classifier: Programming Language :: Python :: 3.12
Classifier: Topic :: Software Development :: Libraries
Classifier: Topic :: System :: Networking
Requires-Python: >=3.9
Requires-Dist: zap-schema>=1.0.0
